{
    "listboxdata" : [
        {
            "title" : "在会员中心页面直接升级",
            "item1" : "在会员中心页面，在相关版本上点击“升级会员”按钮，弹出“支付弹窗”。",
            "item2" : "在弹窗内选择好时长后，扫描二维码进行支付。",
            "item3" : "在弹窗内选择好时长后，扫描二维码进行支付。"
        },
        {
            "title" : "在某些页面底部，点击“升级会员”",
            "item1" : "弹出“支付弹窗”。",
            "item2" : "在弹窗内选择好时长后，扫描二维码进行支付。",
            "item3" : "支付完成后，即为升级完毕。"
        },
        {
            "title" : "在筛选数据时，出现升级弹窗",
            "item1" : "点击“去升级”按钮，弹出“支付弹窗”。",
            "item2" : "在弹窗内选择好时长后，扫描二维码进行支付。",
            "item3" : "支付完成后，即为升级完毕。"
        }
    ],
    "payCarddata" : [
        {
            "header" : {
                "title" : "基础会员",
                "title2" : "适合内容创作和个人运营者",
                "money" : "499",
                "title3" : "年付费更优惠",
                "dataid" : 1
            },
            "content" : [
                [
                    {
                        "title" : "直播数据",
                        "titletext" : [
                            100,500
                        ],
                        "pjudge" : [
                            {
                                "whether" : 1,
                                "text" : "实时流量详情总览数据"
                            },
                            {
                                "whether" : 0,
                                "text" : "直播间商品、观众、商品、数据分析"
                            },
                            {
                                "whether" : 0,
                                "text" : "达人直播分析"
                            }
                        ]
                    }
                ],
                [
                    {
                        "title" : "电商数据",
                        "titletext" : [
                            1500,100,100
                        ],
                        "pjudge" : [
                            {
                                "whether" : 0,
                                "text" : "视频带货电商分析"
                            },
                            {
                                "whether" : 1,
                                "text" : "部分达人电商分析"
                            },
                            {
                                "whether" : 0,
                                "text" : "直播观众与商品分析筛选"
                            }
                        ]
                    }
                ],
                [
                    {
                        "title" : "电商数据",
                        "pjudge" : [
                            {
                                "whether" : 0,
                                "text" : "抖音小店榜"
                            }
                        ]
                    }
                ],
                [
                    {
                        "title" : "电商数据",
                        "titletext" : [
                            1500,100,100
                        ],
                        "pjudge" : [
                            {
                                "whether" : 1,
                                "text" : "星图达人榜"
                            },
                            {
                                "whether" : 1,
                                "text" : "品牌排行榜"
                            },
                            {
                                "whether" : 0,
                                "text" : "直播带货榜"
                            },
                            {
                                "whether" : 0,
                                "text" : "直播带货达人榜"
                            },
                            {
                                "whether" : 0,
                                "text" : "音浪榜"
                            },
                            {
                                "whether" : 1,
                                "text" : "更多维度的部分数据导出"
                            }
                        ]
                    }
                ],
                [
                    {
                        "title" : "其他特权",
                        "privilege" : [
                            {
                                "title" : "主设备登录设备数",
                                "num" : 1
                            },
                            {
                                "title" : "子账号个数",
                                "num" : 0
                            }
                        ]
                    }
                ]
            ]
        },
        {
            "header" : {
                "title" : "豪华会员版",
                "title2" : "适合多账号、资源对接、电商使用",
                "money" : "1399",
                "title3" : "包年更加优惠哦",
                "dataid" : 2
            },
            "content" : [
                [
                    {
                        "title" : "直播数据",
                        "titletext" : [
                            100,500
                        ],
                        "pjudge" : [
                            {
                                "whether" : 1,
                                "text" : "实时流量详情总览数据"
                            },
                            {
                                "whether" : 0,
                                "text" : "直播间商品、观众、商品、数据分析"
                            },
                            {
                                "whether" : 0,
                                "text" : "达人直播分析"
                            }
                        ]
                    }
                ],
                [
                    {
                        "title" : "电商数据",
                        "titletext" : [
                            1500,100,100
                        ],
                        "pjudge" : [
                            {
                                "whether" : 0,
                                "text" : "视频带货电商分析"
                            },
                            {
                                "whether" : 1,
                                "text" : "部分达人电商分析"
                            },
                            {
                                "whether" : 0,
                                "text" : "直播观众与商品分析筛选"
                            }
                        ]
                    }
                ],
                [
                    {
                        "title" : "电商数据",
                        "pjudge" : [
                            {
                                "whether" : 0,
                                "text" : "抖音小店榜"
                            }
                        ]
                    }
                ],
                [
                    {
                        "title" : "电商数据",
                        "titletext" : [
                            1500,100,100
                        ],
                        "pjudge" : [
                            {
                                "whether" : 1,
                                "text" : "星图达人榜"
                            },
                            {
                                "whether" : 1,
                                "text" : "品牌排行榜"
                            },
                            {
                                "whether" : 0,
                                "text" : "直播带货榜"
                            },
                            {
                                "whether" : 0,
                                "text" : "直播带货达人榜"
                            },
                            {
                                "whether" : 0,
                                "text" : "音浪榜"
                            },
                            {
                                "whether" : 1,
                                "text" : "更多维度的部分数据导出"
                            }
                        ]
                    }
                ],
                [
                    {
                        "title" : "其他特权",
                        "privilege" : [
                            {
                                "title" : "主设备登录设备数",
                                "num" : 1
                            },
                            {
                                "title" : "子账号个数",
                                "num" : 0
                            }
                        ]
                    }
                ]
            ]
        },
        {
            "header" : {
                "title" : "超级会员版",
                "title2" : "适用企业多账号管理，推动团队直播变现",
                "money" : "4799",
                "title3" : "包年更加优惠哦",
                "dataid" : 3
            },
            "content" : [
                [
                    {
                        "title" : "直播数据",
                        "titletext" : [
                            100,500
                        ],
                        "pjudge" : [
                            {
                                "whether" : 1,
                                "text" : "实时流量详情总览数据"
                            },
                            {
                                "whether" : 0,
                                "text" : "直播间商品、观众、商品、数据分析"
                            },
                            {
                                "whether" : 0,
                                "text" : "达人直播分析"
                            }
                        ]
                    }
                ],
                [
                    {
                        "title" : "电商数据",
                        "titletext" : [
                            1500,100,100
                        ],
                        "pjudge" : [
                            {
                                "whether" : 0,
                                "text" : "视频带货电商分析"
                            },
                            {
                                "whether" : 1,
                                "text" : "部分达人电商分析"
                            },
                            {
                                "whether" : 0,
                                "text" : "直播观众与商品分析筛选"
                            }
                        ]
                    }
                ],
                [
                    {
                        "title" : "电商数据",
                        "pjudge" : [
                            {
                                "whether" : 0,
                                "text" : "抖音小店榜"
                            }
                        ]
                    }
                ],
                [
                    {
                        "title" : "电商数据",
                        "titletext" : [
                            1500,100,100
                        ],
                        "pjudge" : [
                            {
                                "whether" : 1,
                                "text" : "星图达人榜"
                            },
                            {
                                "whether" : 1,
                                "text" : "品牌排行榜"
                            },
                            {
                                "whether" : 0,
                                "text" : "直播带货榜"
                            },
                            {
                                "whether" : 0,
                                "text" : "直播带货达人榜"
                            },
                            {
                                "whether" : 0,
                                "text" : "音浪榜"
                            },
                            {
                                "whether" : 1,
                                "text" : "更多维度的部分数据导出"
                            }
                        ]
                    }
                ],
                [
                    {
                        "title" : "其他特权",
                        "privilege" : [
                            {
                                "title" : "主设备登录设备数",
                                "num" : 1
                            },
                            {
                                "title" : "子账号个数",
                                "num" : 0
                            }
                        ]
                    }
                ]
            ]
        }
    ]
}